{"errors":[],"warnings":[],"namedChunkGroups":{"polyfill":{"chunks":[0,3],"assets":["webpack-runtime-192cc7829ba4166826a9.js","webpack-runtime-192cc7829ba4166826a9.js.map","polyfill-81d487db101a16aa36cd.js","polyfill-81d487db101a16aa36cd.js.map"],"children":{},"childAssets":{}},"app":{"chunks":[0,2,1],"assets":["webpack-runtime-192cc7829ba4166826a9.js","webpack-runtime-192cc7829ba4166826a9.js.map","framework-6f398f57311141904de7.js","framework-6f398f57311141904de7.js.map","app-a228eb5c973e19ebd9cc.js","app-a228eb5c973e19ebd9cc.js.map"],"children":{},"childAssets":{}}},"assetsByChunkName":{"polyfill":["webpack-runtime-192cc7829ba4166826a9.js","polyfill-81d487db101a16aa36cd.js"],"app":["webpack-runtime-192cc7829ba4166826a9.js","framework-6f398f57311141904de7.js","app-a228eb5c973e19ebd9cc.js"]}}